api_client_framework/__init__.py
api_client_framework/methods.py
api_client_framework/parsers.py
api_client_framework/protocols.py
api_client_framework/requests.py
api_client_framework-0.1.0.dist-info/LICENSE
api_client_framework-0.1.0.dist-info/METADATA
api_client_framework-0.1.0.dist-info/WHEEL
api_client_framework-0.1.0.dist-info/RECORD
