Metadata-Version: 2.1
Name: api_client_framework
Version: 0.1.0
Summary: Class-based helper for constructing API clients
Home-page: https://github.com/EnriqueSoria/python-api-consumer
License: MIT
Author: EnriqueSoria
Author-email: me@enriquesoria.es
Requires-Python: >=3.7,<4.0
Classifier: License :: OSI Approved :: MIT License
Classifier: Programming Language :: Python :: 3
Classifier: Programming Language :: Python :: 3.7
Classifier: Programming Language :: Python :: 3.8
Classifier: Programming Language :: Python :: 3.9
Classifier: Programming Language :: Python :: 3.10
Classifier: Programming Language :: Python :: 3.11
Classifier: Programming Language :: Python :: 3.12
Requires-Dist: requests (>=2.31,<3.0)
Project-URL: Repository, https://github.com/EnriqueSoria/python-api-consumer
